{"resources":{"core":{"limit":5000,"used":75,"remaining":4925,"reset":1746101087},"search":{"limit":30,"used":0,"remaining":30,"reset":1746100863},"graphql":{"limit":5000,"used":0,"remaining":5000,"reset":1746104403},"integration_manifest":{"limit":5000,"used":0,"remaining":5000,"reset":1746104403},"source_import":{"limit":100,"used":0,"remaining":100,"reset":1746100863},"code_scanning_upload":{"limit":5000,"used":75,"remaining":4925,"reset":1746101087},"code_scanning_autofix":{"limit":10,"used":0,"remaining":10,"reset":1746100863},"actions_runner_registration":{"limit":10000,"used":0,"remaining":10000,"reset":1746104403},"scim":{"limit":15000,"used":0,"remaining":15000,"reset":1746104403},"dependency_snapshots":{"limit":100,"used":0,"remaining":100,"reset":1746100863},"audit_log":{"limit":1750,"used":0,"remaining":1750,"reset":1746104403},"audit_log_streaming":{"limit":15,"used":0,"remaining":15,"reset":1746104403},"code_search":{"limit":10,"used":0,"remaining":10,"reset":1746100863}},"rate":{"limit":5000,"used":75,"remaining":4925,"reset":1746101087}}